{"nodes": [{"id": "backend_src_seo_platform_schemas_init_py", "label": "__init__.py", "file_type": "code", "source_file": "backend/src/seo_platform/schemas/__init__.py", "source_location": "L1"}, {"id": "init_apiresponse", "label": "APIResponse", "file_type": "code", "source_file": "backend/src/seo_platform/schemas/__init__.py", "source_location": "L23"}, {"id": "basemodel", "label": "BaseModel", "file_type": "code", "source_file": "", "source_location": ""}, {"id": "init_errordetail", "label": "ErrorDetail", "file_type": "code", "source_file": "backend/src/seo_platform/schemas/__init__.py", "source_location": "L31"}, {"id": "init_responsemeta", "label": "ResponseMeta", "file_type": "code", "source_file": "backend/src/seo_platform/schemas/__init__.py", "source_location": "L39"}, {"id": "init_paginationparams", "label": "PaginationParams", "file_type": "code", "source_file": "backend/src/seo_platform/schemas/__init__.py", "source_location": "L50"}, {"id": "init_tenantcontext", "label": "TenantContext", "file_type": "code", "source_file": "backend/src/seo_platform/schemas/__init__.py", "source_location": "L60"}, {"id": "init_usercontext", "label": "UserContext", "file_type": "code", "source_file": "backend/src/seo_platform/schemas/__init__.py", "source_location": "L67"}, {"id": "init_requestcontext", "label": "RequestContext", "file_type": "code", "source_file": "backend/src/seo_platform/schemas/__init__.py", "source_location": "L77"}, {"id": "init_healthstatus", "label": "HealthStatus", "file_type": "code", "source_file": "backend/src/seo_platform/schemas/__init__.py", "source_location": "L88"}, {"id": "str", "label": "str", "file_type": "code", "source_file": "", "source_location": ""}, {"id": "init_componenthealth", "label": "ComponentHealth", "file_type": "code", "source_file": "backend/src/seo_platform/schemas/__init__.py", "source_location": "L94"}, {"id": "init_healthresponse", "label": "HealthResponse", "file_type": "code", "source_file": "backend/src/seo_platform/schemas/__init__.py", "source_location": "L101"}, {"id": "init_geotarget", "label": "GeoTarget", "file_type": "code", "source_file": "backend/src/seo_platform/schemas/__init__.py", "source_location": "L112"}, {"id": "init_confidencescore", "label": "ConfidenceScore", "file_type": "code", "source_file": "backend/src/seo_platform/schemas/__init__.py", "source_location": "L119"}, {"id": "init_tier", "label": "tier()", "file_type": "code", "source_file": "backend/src/seo_platform/schemas/__init__.py", "source_location": "L126"}, {"id": "init_rationale_1", "label": "SEO Platform \u2014 Shared Pydantic Schemas =========================================", "file_type": "rationale", "source_file": "backend/src/seo_platform/schemas/__init__.py", "source_location": "L1"}, {"id": "init_rationale_24", "label": "Standard API response wrapper for consistency across all endpoints.", "file_type": "rationale", "source_file": "backend/src/seo_platform/schemas/__init__.py", "source_location": "L24"}, {"id": "init_rationale_32", "label": "Structured error payload for API error responses.", "file_type": "rationale", "source_file": "backend/src/seo_platform/schemas/__init__.py", "source_location": "L32"}, {"id": "init_rationale_40", "label": "Pagination and metadata for list responses.", "file_type": "rationale", "source_file": "backend/src/seo_platform/schemas/__init__.py", "source_location": "L40"}, {"id": "init_rationale_51", "label": "Query parameters for paginated list endpoints.", "file_type": "rationale", "source_file": "backend/src/seo_platform/schemas/__init__.py", "source_location": "L51"}, {"id": "init_rationale_61", "label": "Tenant context extracted from auth token \u2014 available in every request.", "file_type": "rationale", "source_file": "backend/src/seo_platform/schemas/__init__.py", "source_location": "L61"}, {"id": "init_rationale_68", "label": "Authenticated user context \u2014 available in every request.", "file_type": "rationale", "source_file": "backend/src/seo_platform/schemas/__init__.py", "source_location": "L68"}, {"id": "init_rationale_78", "label": "Full request context combining tenant + user + trace.", "file_type": "rationale", "source_file": "backend/src/seo_platform/schemas/__init__.py", "source_location": "L78"}, {"id": "init_rationale_113", "label": "Geographic targeting configuration.", "file_type": "rationale", "source_file": "backend/src/seo_platform/schemas/__init__.py", "source_location": "L113"}, {"id": "init_rationale_120", "label": "Confidence assessment for AI-generated outputs.", "file_type": "rationale", "source_file": "backend/src/seo_platform/schemas/__init__.py", "source_location": "L120"}], "edges": [{"source": "backend_src_seo_platform_schemas_init_py", "target": "enum", "relation": "imports", "confidence": "EXTRACTED", "source_file": "backend/src/seo_platform/schemas/__init__.py", "source_location": "L9", "weight": 1.0}, {"source": "backend_src_seo_platform_schemas_init_py", "target": "datetime", "relation": "imports_from", "confidence": "EXTRACTED", "source_file": "backend/src/seo_platform/schemas/__init__.py", "source_location": "L10", "weight": 1.0}, {"source": "backend_src_seo_platform_schemas_init_py", "target": "typing", "relation": "imports_from", "confidence": "EXTRACTED", "source_file": "backend/src/seo_platform/schemas/__init__.py", "source_location": "L11", "weight": 1.0}, {"source": "backend_src_seo_platform_schemas_init_py", "target": "uuid", "relation": "imports_from", "confidence": "EXTRACTED", "source_file": "backend/src/seo_platform/schemas/__init__.py", "source_location": "L12", "weight": 1.0}, {"source": "backend_src_seo_platform_schemas_init_py", "target": "pydantic", "relation": "imports_from", "confidence": "EXTRACTED", "source_file": "backend/src/seo_platform/schemas/__init__.py", "source_location": "L14", "weight": 1.0}, {"source": "backend_src_seo_platform_schemas_init_py", "target": "init_apiresponse", "relation": "contains", "confidence": "EXTRACTED", "source_file": "backend/src/seo_platform/schemas/__init__.py", "source_location": "L23", "weight": 1.0}, {"source": "init_apiresponse", "target": "basemodel", "relation": "inherits", "confidence": "EXTRACTED", "source_file": "backend/src/seo_platform/schemas/__init__.py", "source_location": "L23", "weight": 1.0}, {"source": "backend_src_seo_platform_schemas_init_py", "target": "init_errordetail", "relation": "contains", "confidence": "EXTRACTED", "source_file": "backend/src/seo_platform/schemas/__init__.py", "source_location": "L31", "weight": 1.0}, {"source": "init_errordetail", "target": "basemodel", "relation": "inherits", "confidence": "EXTRACTED", "source_file": "backend/src/seo_platform/schemas/__init__.py", "source_location": "L31", "weight": 1.0}, {"source": "backend_src_seo_platform_schemas_init_py", "target": "init_responsemeta", "relation": "contains", "confidence": "EXTRACTED", "source_file": "backend/src/seo_platform/schemas/__init__.py", "source_location": "L39", "weight": 1.0}, {"source": "init_responsemeta", "target": "basemodel", "relation": "inherits", "confidence": "EXTRACTED", "source_file": "backend/src/seo_platform/schemas/__init__.py", "source_location": "L39", "weight": 1.0}, {"source": "backend_src_seo_platform_schemas_init_py", "target": "init_paginationparams", "relation": "contains", "confidence": "EXTRACTED", "source_file": "backend/src/seo_platform/schemas/__init__.py", "source_location": "L50", "weight": 1.0}, {"source": "init_paginationparams", "target": "basemodel", "relation": "inherits", "confidence": "EXTRACTED", "source_file": "backend/src/seo_platform/schemas/__init__.py", "source_location": "L50", "weight": 1.0}, {"source": "backend_src_seo_platform_schemas_init_py", "target": "init_tenantcontext", "relation": "contains", "confidence": "EXTRACTED", "source_file": "backend/src/seo_platform/schemas/__init__.py", "source_location": "L60", "weight": 1.0}, {"source": "init_tenantcontext", "target": "basemodel", "relation": "inherits", "confidence": "EXTRACTED", "source_file": "backend/src/seo_platform/schemas/__init__.py", "source_location": "L60", "weight": 1.0}, {"source": "backend_src_seo_platform_schemas_init_py", "target": "init_usercontext", "relation": "contains", "confidence": "EXTRACTED", "source_file": "backend/src/seo_platform/schemas/__init__.py", "source_location": "L67", "weight": 1.0}, {"source": "init_usercontext", "target": "basemodel", "relation": "inherits", "confidence": "EXTRACTED", "source_file": "backend/src/seo_platform/schemas/__init__.py", "source_location": "L67", "weight": 1.0}, {"source": "backend_src_seo_platform_schemas_init_py", "target": "init_requestcontext", "relation": "contains", "confidence": "EXTRACTED", "source_file": "backend/src/seo_platform/schemas/__init__.py", "source_location": "L77", "weight": 1.0}, {"source": "init_requestcontext", "target": "basemodel", "relation": "inherits", "confidence": "EXTRACTED", "source_file": "backend/src/seo_platform/schemas/__init__.py", "source_location": "L77", "weight": 1.0}, {"source": "backend_src_seo_platform_schemas_init_py", "target": "init_healthstatus", "relation": "contains", "confidence": "EXTRACTED", "source_file": "backend/src/seo_platform/schemas/__init__.py", "source_location": "L88", "weight": 1.0}, {"source": "init_healthstatus", "target": "str", "relation": "inherits", "confidence": "EXTRACTED", "source_file": "backend/src/seo_platform/schemas/__init__.py", "source_location": "L88", "weight": 1.0}, {"source": "backend_src_seo_platform_schemas_init_py", "target": "init_componenthealth", "relation": "contains", "confidence": "EXTRACTED", "source_file": "backend/src/seo_platform/schemas/__init__.py", "source_location": "L94", "weight": 1.0}, {"source": "init_componenthealth", "target": "basemodel", "relation": "inherits", "confidence": "EXTRACTED", "source_file": "backend/src/seo_platform/schemas/__init__.py", "source_location": "L94", "weight": 1.0}, {"source": "backend_src_seo_platform_schemas_init_py", "target": "init_healthresponse", "relation": "contains", "confidence": "EXTRACTED", "source_file": "backend/src/seo_platform/schemas/__init__.py", "source_location": "L101", "weight": 1.0}, {"source": "init_healthresponse", "target": "basemodel", "relation": "inherits", "confidence": "EXTRACTED", "source_file": "backend/src/seo_platform/schemas/__init__.py", "source_location": "L101", "weight": 1.0}, {"source": "backend_src_seo_platform_schemas_init_py", "target": "init_geotarget", "relation": "contains", "confidence": "EXTRACTED", "source_file": "backend/src/seo_platform/schemas/__init__.py", "source_location": "L112", "weight": 1.0}, {"source": "init_geotarget", "target": "basemodel", "relation": "inherits", "confidence": "EXTRACTED", "source_file": "backend/src/seo_platform/schemas/__init__.py", "source_location": "L112", "weight": 1.0}, {"source": "backend_src_seo_platform_schemas_init_py", "target": "init_confidencescore", "relation": "contains", "confidence": "EXTRACTED", "source_file": "backend/src/seo_platform/schemas/__init__.py", "source_location": "L119", "weight": 1.0}, {"source": "init_confidencescore", "target": "basemodel", "relation": "inherits", "confidence": "EXTRACTED", "source_file": "backend/src/seo_platform/schemas/__init__.py", "source_location": "L119", "weight": 1.0}, {"source": "backend_src_seo_platform_schemas_init_py", "target": "init_tier", "relation": "contains", "confidence": "EXTRACTED", "source_file": "backend/src/seo_platform/schemas/__init__.py", "source_location": "L126", "weight": 1.0}, {"source": "init_rationale_1", "target": "backend_src_seo_platform_schemas_init_py", "relation": "rationale_for", "confidence": "EXTRACTED", "source_file": "backend/src/seo_platform/schemas/__init__.py", "source_location": "L1", "weight": 1.0}, {"source": "init_rationale_24", "target": "init_apiresponse", "relation": "rationale_for", "confidence": "EXTRACTED", "source_file": "backend/src/seo_platform/schemas/__init__.py", "source_location": "L24", "weight": 1.0}, {"source": "init_rationale_32", "target": "init_errordetail", "relation": "rationale_for", "confidence": "EXTRACTED", "source_file": "backend/src/seo_platform/schemas/__init__.py", "source_location": "L32", "weight": 1.0}, {"source": "init_rationale_40", "target": "init_responsemeta", "relation": "rationale_for", "confidence": "EXTRACTED", "source_file": "backend/src/seo_platform/schemas/__init__.py", "source_location": "L40", "weight": 1.0}, {"source": "init_rationale_51", "target": "init_paginationparams", "relation": "rationale_for", "confidence": "EXTRACTED", "source_file": "backend/src/seo_platform/schemas/__init__.py", "source_location": "L51", "weight": 1.0}, {"source": "init_rationale_61", "target": "init_tenantcontext", "relation": "rationale_for", "confidence": "EXTRACTED", "source_file": "backend/src/seo_platform/schemas/__init__.py", "source_location": "L61", "weight": 1.0}, {"source": "init_rationale_68", "target": "init_usercontext", "relation": "rationale_for", "confidence": "EXTRACTED", "source_file": "backend/src/seo_platform/schemas/__init__.py", "source_location": "L68", "weight": 1.0}, {"source": "init_rationale_78", "target": "init_requestcontext", "relation": "rationale_for", "confidence": "EXTRACTED", "source_file": "backend/src/seo_platform/schemas/__init__.py", "source_location": "L78", "weight": 1.0}, {"source": "init_rationale_113", "target": "init_geotarget", "relation": "rationale_for", "confidence": "EXTRACTED", "source_file": "backend/src/seo_platform/schemas/__init__.py", "source_location": "L113", "weight": 1.0}, {"source": "init_rationale_120", "target": "init_confidencescore", "relation": "rationale_for", "confidence": "EXTRACTED", "source_file": "backend/src/seo_platform/schemas/__init__.py", "source_location": "L120", "weight": 1.0}], "raw_calls": []}