{"nodes": [{"id": "backend_src_seo_platform_api_endpoints_realtime_sse_py", "label": "sse.py", "file_type": "code", "source_file": "backend/src/seo_platform/api/endpoints/realtime/sse.py", "source_location": "L1"}, {"id": "sse_ssemanager", "label": "SSEManager", "file_type": "code", "source_file": "backend/src/seo_platform/api/endpoints/realtime/sse.py", "source_location": "L23"}, {"id": "sse_ssemanager_init", "label": ".__init__()", "file_type": "code", "source_file": "backend/src/seo_platform/api/endpoints/realtime/sse.py", "source_location": "L28"}, {"id": "sse_ssemanager_subscribe", "label": ".subscribe()", "file_type": "code", "source_file": "backend/src/seo_platform/api/endpoints/realtime/sse.py", "source_location": "L31"}, {"id": "sse_ssemanager_unsubscribe", "label": ".unsubscribe()", "file_type": "code", "source_file": "backend/src/seo_platform/api/endpoints/realtime/sse.py", "source_location": "L38"}, {"id": "sse_ssemanager_publish", "label": ".publish()", "file_type": "code", "source_file": "backend/src/seo_platform/api/endpoints/realtime/sse.py", "source_location": "L46"}, {"id": "sse_ssemanager_broadcast", "label": ".broadcast()", "file_type": "code", "source_file": "backend/src/seo_platform/api/endpoints/realtime/sse.py", "source_location": "L57"}, {"id": "sse_event_generator", "label": "event_generator()", "file_type": "code", "source_file": "backend/src/seo_platform/api/endpoints/realtime/sse.py", "source_location": "L72"}, {"id": "sse_stream_events", "label": "stream_events()", "file_type": "code", "source_file": "backend/src/seo_platform/api/endpoints/realtime/sse.py", "source_location": "L91"}, {"id": "sse_emit_workflow_event", "label": "emit_workflow_event()", "file_type": "code", "source_file": "backend/src/seo_platform/api/endpoints/realtime/sse.py", "source_location": "L113"}, {"id": "sse_emit_approval_event", "label": "emit_approval_event()", "file_type": "code", "source_file": "backend/src/seo_platform/api/endpoints/realtime/sse.py", "source_location": "L128"}, {"id": "sse_emit_campaign_event", "label": "emit_campaign_event()", "file_type": "code", "source_file": "backend/src/seo_platform/api/endpoints/realtime/sse.py", "source_location": "L142"}, {"id": "sse_emit_infra_event", "label": "emit_infra_event()", "file_type": "code", "source_file": "backend/src/seo_platform/api/endpoints/realtime/sse.py", "source_location": "L156"}, {"id": "sse_rationale_1", "label": "SEO Platform \u2014 Server-Sent Events (SSE) Real-time Updates ======================", "file_type": "rationale", "source_file": "backend/src/seo_platform/api/endpoints/realtime/sse.py", "source_location": "L1"}, {"id": "sse_rationale_24", "label": "Manages SSE connections for real-time updates.", "file_type": "rationale", "source_file": "backend/src/seo_platform/api/endpoints/realtime/sse.py", "source_location": "L24"}, {"id": "sse_rationale_32", "label": "Subscribe a connection to a channel.", "file_type": "rationale", "source_file": "backend/src/seo_platform/api/endpoints/realtime/sse.py", "source_location": "L32"}, {"id": "sse_rationale_39", "label": "Unsubscribe a connection from a channel.", "file_type": "rationale", "source_file": "backend/src/seo_platform/api/endpoints/realtime/sse.py", "source_location": "L39"}, {"id": "sse_rationale_47", "label": "Publish an event to all subscribers of a channel.", "file_type": "rationale", "source_file": "backend/src/seo_platform/api/endpoints/realtime/sse.py", "source_location": "L47"}, {"id": "sse_rationale_58", "label": "Broadcast to all tenants on a specific channel.", "file_type": "rationale", "source_file": "backend/src/seo_platform/api/endpoints/realtime/sse.py", "source_location": "L58"}, {"id": "sse_rationale_73", "label": "Generate SSE events for a client.", "file_type": "rationale", "source_file": "backend/src/seo_platform/api/endpoints/realtime/sse.py", "source_location": "L73"}, {"id": "sse_rationale_95", "label": "SSE endpoint for real-time updates.          Subscribe to channels: workflows, a", "file_type": "rationale", "source_file": "backend/src/seo_platform/api/endpoints/realtime/sse.py", "source_location": "L95"}, {"id": "sse_rationale_114", "label": "Publish workflow event to subscribers.", "file_type": "rationale", "source_file": "backend/src/seo_platform/api/endpoints/realtime/sse.py", "source_location": "L114"}, {"id": "sse_rationale_129", "label": "Publish approval event to subscribers.", "file_type": "rationale", "source_file": "backend/src/seo_platform/api/endpoints/realtime/sse.py", "source_location": "L129"}, {"id": "sse_rationale_143", "label": "Publish campaign event to subscribers.", "file_type": "rationale", "source_file": "backend/src/seo_platform/api/endpoints/realtime/sse.py", "source_location": "L143"}, {"id": "sse_rationale_157", "label": "Publish infrastructure health event.", "file_type": "rationale", "source_file": "backend/src/seo_platform/api/endpoints/realtime/sse.py", "source_location": "L157"}], "edges": [{"source": "backend_src_seo_platform_api_endpoints_realtime_sse_py", "target": "asyncio", "relation": "imports", "confidence": "EXTRACTED", "source_file": "backend/src/seo_platform/api/endpoints/realtime/sse.py", "source_location": "L8", "weight": 1.0}, {"source": "backend_src_seo_platform_api_endpoints_realtime_sse_py", "target": "json", "relation": "imports", "confidence": "EXTRACTED", "source_file": "backend/src/seo_platform/api/endpoints/realtime/sse.py", "source_location": "L9", "weight": 1.0}, {"source": "backend_src_seo_platform_api_endpoints_realtime_sse_py", "target": "typing", "relation": "imports_from", "confidence": "EXTRACTED", "source_file": "backend/src/seo_platform/api/endpoints/realtime/sse.py", "source_location": "L10", "weight": 1.0}, {"source": "backend_src_seo_platform_api_endpoints_realtime_sse_py", "target": "uuid", "relation": "imports_from", "confidence": "EXTRACTED", "source_file": "backend/src/seo_platform/api/endpoints/realtime/sse.py", "source_location": "L11", "weight": 1.0}, {"source": "backend_src_seo_platform_api_endpoints_realtime_sse_py", "target": "fastapi", "relation": "imports_from", "confidence": "EXTRACTED", "source_file": "backend/src/seo_platform/api/endpoints/realtime/sse.py", "source_location": "L13", "weight": 1.0}, {"source": "backend_src_seo_platform_api_endpoints_realtime_sse_py", "target": "fastapi_responses", "relation": "imports_from", "confidence": "EXTRACTED", "source_file": "backend/src/seo_platform/api/endpoints/realtime/sse.py", "source_location": "L14", "weight": 1.0}, {"source": "backend_src_seo_platform_api_endpoints_realtime_sse_py", "target": "seo_platform_core_logging", "relation": "imports_from", "confidence": "EXTRACTED", "source_file": "backend/src/seo_platform/api/endpoints/realtime/sse.py", "source_location": "L16", "weight": 1.0}, {"source": "backend_src_seo_platform_api_endpoints_realtime_sse_py", "target": "sse_ssemanager", "relation": "contains", "confidence": "EXTRACTED", "source_file": "backend/src/seo_platform/api/endpoints/realtime/sse.py", "source_location": "L23", "weight": 1.0}, {"source": "sse_ssemanager", "target": "sse_ssemanager_init", "relation": "method", "confidence": "EXTRACTED", "source_file": "backend/src/seo_platform/api/endpoints/realtime/sse.py", "source_location": "L28", "weight": 1.0}, {"source": "sse_ssemanager", "target": "sse_ssemanager_subscribe", "relation": "method", "confidence": "EXTRACTED", "source_file": "backend/src/seo_platform/api/endpoints/realtime/sse.py", "source_location": "L31", "weight": 1.0}, {"source": "sse_ssemanager", "target": "sse_ssemanager_unsubscribe", "relation": "method", "confidence": "EXTRACTED", "source_file": "backend/src/seo_platform/api/endpoints/realtime/sse.py", "source_location": "L38", "weight": 1.0}, {"source": "sse_ssemanager", "target": "sse_ssemanager_publish", "relation": "method", "confidence": "EXTRACTED", "source_file": "backend/src/seo_platform/api/endpoints/realtime/sse.py", "source_location": "L46", "weight": 1.0}, {"source": "sse_ssemanager", "target": "sse_ssemanager_broadcast", "relation": "method", "confidence": "EXTRACTED", "source_file": "backend/src/seo_platform/api/endpoints/realtime/sse.py", "source_location": "L57", "weight": 1.0}, {"source": "backend_src_seo_platform_api_endpoints_realtime_sse_py", "target": "sse_event_generator", "relation": "contains", "confidence": "EXTRACTED", "source_file": "backend/src/seo_platform/api/endpoints/realtime/sse.py", "source_location": "L72", "weight": 1.0}, {"source": "backend_src_seo_platform_api_endpoints_realtime_sse_py", "target": "sse_stream_events", "relation": "contains", "confidence": "EXTRACTED", "source_file": "backend/src/seo_platform/api/endpoints/realtime/sse.py", "source_location": "L91", "weight": 1.0}, {"source": "backend_src_seo_platform_api_endpoints_realtime_sse_py", "target": "sse_emit_workflow_event", "relation": "contains", "confidence": "EXTRACTED", "source_file": "backend/src/seo_platform/api/endpoints/realtime/sse.py", "source_location": "L113", "weight": 1.0}, {"source": "backend_src_seo_platform_api_endpoints_realtime_sse_py", "target": "sse_emit_approval_event", "relation": "contains", "confidence": "EXTRACTED", "source_file": "backend/src/seo_platform/api/endpoints/realtime/sse.py", "source_location": "L128", "weight": 1.0}, {"source": "backend_src_seo_platform_api_endpoints_realtime_sse_py", "target": "sse_emit_campaign_event", "relation": "contains", "confidence": "EXTRACTED", "source_file": "backend/src/seo_platform/api/endpoints/realtime/sse.py", "source_location": "L142", "weight": 1.0}, {"source": "backend_src_seo_platform_api_endpoints_realtime_sse_py", "target": "sse_emit_infra_event", "relation": "contains", "confidence": "EXTRACTED", "source_file": "backend/src/seo_platform/api/endpoints/realtime/sse.py", "source_location": "L156", "weight": 1.0}, {"source": "sse_event_generator", "target": "sse_ssemanager_subscribe", "relation": "calls", "confidence": "EXTRACTED", "source_file": "backend/src/seo_platform/api/endpoints/realtime/sse.py", "source_location": "L77", "weight": 1.0}, {"source": "sse_event_generator", "target": "sse_ssemanager_unsubscribe", "relation": "calls", "confidence": "EXTRACTED", "source_file": "backend/src/seo_platform/api/endpoints/realtime/sse.py", "source_location": "L87", "weight": 1.0}, {"source": "sse_stream_events", "target": "sse_event_generator", "relation": "calls", "confidence": "EXTRACTED", "source_file": "backend/src/seo_platform/api/endpoints/realtime/sse.py", "source_location": "L103", "weight": 1.0}, {"source": "sse_emit_workflow_event", "target": "sse_ssemanager_publish", "relation": "calls", "confidence": "EXTRACTED", "source_file": "backend/src/seo_platform/api/endpoints/realtime/sse.py", "source_location": "L115", "weight": 1.0}, {"source": "sse_emit_approval_event", "target": "sse_ssemanager_publish", "relation": "calls", "confidence": "EXTRACTED", "source_file": "backend/src/seo_platform/api/endpoints/realtime/sse.py", "source_location": "L130", "weight": 1.0}, {"source": "sse_emit_campaign_event", "target": "sse_ssemanager_publish", "relation": "calls", "confidence": "EXTRACTED", "source_file": "backend/src/seo_platform/api/endpoints/realtime/sse.py", "source_location": "L144", "weight": 1.0}, {"source": "sse_emit_infra_event", "target": "sse_ssemanager_broadcast", "relation": "calls", "confidence": "EXTRACTED", "source_file": "backend/src/seo_platform/api/endpoints/realtime/sse.py", "source_location": "L158", "weight": 1.0}, {"source": "sse_rationale_1", "target": "backend_src_seo_platform_api_endpoints_realtime_sse_py", "relation": "rationale_for", "confidence": "EXTRACTED", "source_file": "backend/src/seo_platform/api/endpoints/realtime/sse.py", "source_location": "L1", "weight": 1.0}, {"source": "sse_rationale_24", "target": "sse_ssemanager", "relation": "rationale_for", "confidence": "EXTRACTED", "source_file": "backend/src/seo_platform/api/endpoints/realtime/sse.py", "source_location": "L24", "weight": 1.0}, {"source": "sse_rationale_32", "target": "sse_ssemanager_subscribe", "relation": "rationale_for", "confidence": "EXTRACTED", "source_file": "backend/src/seo_platform/api/endpoints/realtime/sse.py", "source_location": "L32", "weight": 1.0}, {"source": "sse_rationale_39", "target": "sse_ssemanager_unsubscribe", "relation": "rationale_for", "confidence": "EXTRACTED", "source_file": "backend/src/seo_platform/api/endpoints/realtime/sse.py", "source_location": "L39", "weight": 1.0}, {"source": "sse_rationale_47", "target": "sse_ssemanager_publish", "relation": "rationale_for", "confidence": "EXTRACTED", "source_file": "backend/src/seo_platform/api/endpoints/realtime/sse.py", "source_location": "L47", "weight": 1.0}, {"source": "sse_rationale_58", "target": "sse_ssemanager_broadcast", "relation": "rationale_for", "confidence": "EXTRACTED", "source_file": "backend/src/seo_platform/api/endpoints/realtime/sse.py", "source_location": "L58", "weight": 1.0}, {"source": "sse_rationale_73", "target": "sse_event_generator", "relation": "rationale_for", "confidence": "EXTRACTED", "source_file": "backend/src/seo_platform/api/endpoints/realtime/sse.py", "source_location": "L73", "weight": 1.0}, {"source": "sse_rationale_95", "target": "sse_stream_events", "relation": "rationale_for", "confidence": "EXTRACTED", "source_file": "backend/src/seo_platform/api/endpoints/realtime/sse.py", "source_location": "L95", "weight": 1.0}, {"source": "sse_rationale_114", "target": "sse_emit_workflow_event", "relation": "rationale_for", "confidence": "EXTRACTED", "source_file": "backend/src/seo_platform/api/endpoints/realtime/sse.py", "source_location": "L114", "weight": 1.0}, {"source": "sse_rationale_129", "target": "sse_emit_approval_event", "relation": "rationale_for", "confidence": "EXTRACTED", "source_file": "backend/src/seo_platform/api/endpoints/realtime/sse.py", "source_location": "L129", "weight": 1.0}, {"source": "sse_rationale_143", "target": "sse_emit_campaign_event", "relation": "rationale_for", "confidence": "EXTRACTED", "source_file": "backend/src/seo_platform/api/endpoints/realtime/sse.py", "source_location": "L143", "weight": 1.0}, {"source": "sse_rationale_157", "target": "sse_emit_infra_event", "relation": "rationale_for", "confidence": "EXTRACTED", "source_file": "backend/src/seo_platform/api/endpoints/realtime/sse.py", "source_location": "L157", "weight": 1.0}], "raw_calls": [{"caller_nid": "sse_ssemanager_subscribe", "callee": "set", "source_file": "backend/src/seo_platform/api/endpoints/realtime/sse.py", "source_location": "L35"}, {"caller_nid": "sse_ssemanager_subscribe", "callee": "add", "source_file": "backend/src/seo_platform/api/endpoints/realtime/sse.py", "source_location": "L36"}, {"caller_nid": "sse_ssemanager_unsubscribe", "callee": "discard", "source_file": "backend/src/seo_platform/api/endpoints/realtime/sse.py", "source_location": "L42"}, {"caller_nid": "sse_ssemanager_publish", "callee": "dumps", "source_file": "backend/src/seo_platform/api/endpoints/realtime/sse.py", "source_location": "L50"}, {"caller_nid": "sse_ssemanager_publish", "callee": "put", "source_file": "backend/src/seo_platform/api/endpoints/realtime/sse.py", "source_location": "L53"}, {"caller_nid": "sse_ssemanager_publish", "callee": "warning", "source_file": "backend/src/seo_platform/api/endpoints/realtime/sse.py", "source_location": "L55"}, {"caller_nid": "sse_ssemanager_publish", "callee": "str", "source_file": "backend/src/seo_platform/api/endpoints/realtime/sse.py", "source_location": "L55"}, {"caller_nid": "sse_ssemanager_broadcast", "callee": "items", "source_file": "backend/src/seo_platform/api/endpoints/realtime/sse.py", "source_location": "L59"}, {"caller_nid": "sse_ssemanager_broadcast", "callee": "endswith", "source_file": "backend/src/seo_platform/api/endpoints/realtime/sse.py", "source_location": "L60"}, {"caller_nid": "sse_ssemanager_broadcast", "callee": "dumps", "source_file": "backend/src/seo_platform/api/endpoints/realtime/sse.py", "source_location": "L61"}, {"caller_nid": "sse_ssemanager_broadcast", "callee": "put", "source_file": "backend/src/seo_platform/api/endpoints/realtime/sse.py", "source_location": "L64"}, {"caller_nid": "sse_event_generator", "callee": "Queue", "source_file": "backend/src/seo_platform/api/endpoints/realtime/sse.py", "source_location": "L74"}, {"caller_nid": "sse_event_generator", "callee": "wait_for", "source_file": "backend/src/seo_platform/api/endpoints/realtime/sse.py", "source_location": "L81"}, {"caller_nid": "sse_event_generator", "callee": "get", "source_file": "backend/src/seo_platform/api/endpoints/realtime/sse.py", "source_location": "L81"}, {"caller_nid": "sse_stream_events", "callee": "split", "source_file": "backend/src/seo_platform/api/endpoints/realtime/sse.py", "source_location": "L100"}, {"caller_nid": "sse_stream_events", "callee": "StreamingResponse", "source_file": "backend/src/seo_platform/api/endpoints/realtime/sse.py", "source_location": "L102"}, {"caller_nid": "sse_emit_workflow_event", "callee": "str", "source_file": "backend/src/seo_platform/api/endpoints/realtime/sse.py", "source_location": "L116"}, {"caller_nid": "sse_emit_workflow_event", "callee": "time", "source_file": "backend/src/seo_platform/api/endpoints/realtime/sse.py", "source_location": "L123"}, {"caller_nid": "sse_emit_workflow_event", "callee": "get_event_loop", "source_file": "backend/src/seo_platform/api/endpoints/realtime/sse.py", "source_location": "L123"}, {"caller_nid": "sse_emit_approval_event", "callee": "str", "source_file": "backend/src/seo_platform/api/endpoints/realtime/sse.py", "source_location": "L131"}, {"caller_nid": "sse_emit_approval_event", "callee": "time", "source_file": "backend/src/seo_platform/api/endpoints/realtime/sse.py", "source_location": "L137"}, {"caller_nid": "sse_emit_approval_event", "callee": "get_event_loop", "source_file": "backend/src/seo_platform/api/endpoints/realtime/sse.py", "source_location": "L137"}, {"caller_nid": "sse_emit_campaign_event", "callee": "str", "source_file": "backend/src/seo_platform/api/endpoints/realtime/sse.py", "source_location": "L145"}, {"caller_nid": "sse_emit_campaign_event", "callee": "time", "source_file": "backend/src/seo_platform/api/endpoints/realtime/sse.py", "source_location": "L151"}, {"caller_nid": "sse_emit_campaign_event", "callee": "get_event_loop", "source_file": "backend/src/seo_platform/api/endpoints/realtime/sse.py", "source_location": "L151"}, {"caller_nid": "sse_emit_infra_event", "callee": "time", "source_file": "backend/src/seo_platform/api/endpoints/realtime/sse.py", "source_location": "L164"}, {"caller_nid": "sse_emit_infra_event", "callee": "get_event_loop", "source_file": "backend/src/seo_platform/api/endpoints/realtime/sse.py", "source_location": "L164"}]}